diodedance/__init__.py
diodedance-0.1.0.dist-info/METADATA
diodedance-0.1.0.dist-info/WHEEL
diodedance-0.1.0.dist-info/RECORD
